LICENSE
MANIFEST.in
README.md
requirements.txt
setup.cfg
setup.py
gcdt_lookups/__init__.py
gcdt_lookups/credstash_utils.py
gcdt_lookups/lookups.py
gcdt_lookups.egg-info/PKG-INFO
gcdt_lookups.egg-info/SOURCES.txt
gcdt_lookups.egg-info/dependency_links.txt
gcdt_lookups.egg-info/entry_points.txt
gcdt_lookups.egg-info/requires.txt
gcdt_lookups.egg-info/top_level.txt