Metadata-Version: 1.1
Name: gcdt-lookups
Version: 0.0.25
Summary: Plugin (gcdt-lookups) for gcdt
Home-page: UNKNOWN
Author: glomex SRE Team
Author-email: mark.fink@glomex.com
License: MIT
Platform: UNKNOWN
Classifier: Natural Language :: English
Classifier: Intended Audience :: Developers
Classifier: Environment :: Console
Classifier: License :: OSI Approved :: MIT License
Classifier: Programming Language :: Python :: 2.7
Classifier: Programming Language :: Python :: 3.6
